leb128/__init__.py
leb128-1.0.6.dist-info/LICENSE
leb128-1.0.6.dist-info/METADATA
leb128-1.0.6.dist-info/WHEEL
leb128-1.0.6.dist-info/top_level.txt
leb128-1.0.6.dist-info/RECORD
