Metadata-Version: 2.1
Name: leb128
Version: 1.0.6
Summary: LEB128(Little Endian Base 128)
Author-email: Mohanson <mohanson@outlook.com>
License: MIT License
Project-URL: homepage, https://github.com/mohanson/leb128
License-File: LICENSE
